Workbook

Sheet Gia Dinh Dau Vao
B2: MÔ HÌNH DỰ TOÁN TÀI CHÍNH & THỜI GIAN HỒI VỐN - VIBESURVEY
B3: Lưu ý: Các ô màu vàng nhạt [ ] là ô bạn có thể tự do thay đổi số liệu. Các ô còn lại tự động tính toán theo công thức.
B5: I. CHI PHÍ ĐẦU TƯ BAN ĐẦU (CAPEX - TRẢ 1 LẦN DUY NHẤT)
B6: Hạng Mục Chi Phí Khởi Tạo | C6: Số Tiền (VNĐ) | D6: Đơn Vị | E6: Ghi Chú Giải Thích Thực Tế
B7: Tài khoản Google Play Developer (25 USD) | C7: 630000 | D7: Phí 1 lần | E7: Đăng ký quyền phát hành APK trên Google Play Console
B8: Mua Tên Miền (.vn hoặc .com) năm đầu | C8: 350000 | D8: Phí 1 lần | E8: Tên miền thương hiệu chính thức (VD: vibesurvey.vn)
B9: Đăng ký kinh doanh & Thông báo Bộ Công Thương | C9: 1500000 | D9: Phí 1 lần | E9: Đăng ký website sàn TMĐT cung cấp dịch vụ trực tuyến
B10: Tích hợp Cổng Thanh Toán VietQR / Payout | C10: 500000 | D10: Phí 1 lần | E10: Phí kích hoạt webhook đối soát ngân hàng tự động
B11: Quỹ Thanh Khoản Trả Thưởng Mồi Ban Đầu | C11: 5000000 | D11: Vốn lưu động | E11: Tiền mặt có sẵn trong tài khoản để người dùng rút được ngay
B12: Chi phí dự phòng khởi tạo khác | C12: 1000000 | D12: Dự phòng | E12: Thiết kế nhận diện, server test, bảo mật ban đầu
B13: TỔNG VỐN ĐẦU TƯ BAN ĐẦU (TOTAL CAPEX) | C13: =SUM(C7:C12) -> 0 | D13: VNĐ | E13: Tổng số vốn tiền mặt cần có sẵn để bắt đầu vận hành
B15: II. GIẢ ĐỊNH NGƯỜI TẠO KHẢO SÁT NẠP TIỀN HÀNG THÁNG (CREATOR DEPOSITS)
B16: Phân Khúc Khách Hàng | C16: Số Người Nạp / Tháng | D16: Mức Nạp TB (VNĐ) | E16: Ghi Chú Đặc Thù Phân Khúc
B17: 1. Sinh Viên (.edu.vn) - Đề tài NCKH, Khóa luận | C17: 80 | D17: 45000 | E17: Mốc nạp 20k - 50k gom 50 - 100 mẫu khảo sát
B18: 2. Cá Nhân / Nghiên cứu thị trường độc lập | C18: 40 | D18: 150000 | E18: Mốc nạp 100k - 200k gom 100 - 200 mẫu tiêu chuẩn
B19: 3. Doanh Nghiệp Vừa & Nhỏ (SME / Startup) | C19: 10 | D19: 800000 | E19: Mốc nạp 500k - 1M gom 300 - 500 mẫu
B20: 4. Doanh Nghiệp Lớn (Enterprise B2B) | C20: 2 | D20: 3000000 | E20: Gói 2M - 5M gom 1.000+ mẫu, bảo hành 1-1, xuất VAT
B21: Tổng Người Nạp & Tổng Tiền Nạp (GMV / Ký Quỹ) | C21: =SUM(C17:C20) -> 0 | D21: =(C17*D17)+(C18*D18)+(C19*D19)+(C20*D20) -> 0 | E21: Tổng số tiền Creator nạp vào ví Credit trên sàn mỗi tháng
B23: III. BIÊN LỢI NHUẬN SÀN (TAKE-RATE) & NGUỒN THU PHỤ TRỢ
B24: Nguồn Doanh Thu Bổ Trợ Của Sàn | C24: Giá Trị Giả Định | D24: Đơn Vị | E24: Ghi Chú Thực Tế Vận Hành
B25: Tỷ lệ chiết khấu sàn bình quân (Avg Take-Rate) | C25: 0.3 | D25: % trên GMV | E25: Sàn giữ lại bình quân 30% tiền mẫu, 70% trả cho đáp viên
B26: Số gói Ghim VIP + Push APK bán được / tháng | C26: 15 | D26: Gói (40k/gói) | E26: Creator mua để gom mẫu hỏa tốc (Biên lợi nhuận > 90%)
B27: Tổng giá trị Voucher Creator mua từ kho sàn | C27: 3000000 | D27: VNĐ / tháng | E27: Creator mua mã E-Voucher để tặng kèm người làm bài
B28: Hoa hồng chiết khấu bán Voucher thương hiệu | C28: 0.08 | D28: % hoa hồng | E28: Chiết khấu từ nhà phát hành voucher (Got It, UrBox, Shopee)
B29: Số lệnh rút tiền dưới 100k có thu phí 2.000đ | C29: 120 | D29: Lệnh / tháng | E29: Phí xử lý giao dịch rút tiền dưới 100.000đ
B31: IV. CHI PHÍ DUY TRÌ HÀNG THÁNG (OPEX: HẠ TẦNG, NHÂN SỰ, MARKETING)
B32: Khoản Mục Chi Phí Vận Hành Hàng Tháng | C32: Chi Phí (VNĐ) | D32: Tính Chất | E32: Ghi Chú Cụ Thể
B33: 1. Thuê Máy Chủ VPS (Cloud Server Node.js + DB) | C33: 250000 | D33: Cố định | E33: VPS 2 Core, 4GB RAM (Hetzner / Vietnix / Oracle Cloud)
B34: 2. Dịch vụ Email Transactional OTP (Brevo / SES) | C34: 100000 | D34: Cố định | E34: Gửi email xác thực OTP đăng ký & OTP sinh viên edu
B35: 3. Cổng đối soát VietQR tự động (PayOS / Casso) | C35: 100000 | D35: Cố định | E35: Webhook xác nhận tiền nạp Creator 24/7 tức thì
B36: 4. Lưu trữ đám mây Cloudflare R2 & Tên miền/tháng | C36: 50000 | D36: Cố định | E36: Lưu ảnh khảo sát, zero egress fee + phân bổ tên miền
B37: 5. Lương Nhân Sự (Vận hành, CSKH, Kiểm duyệt form) | C37: 3000000 | D37: Nhân sự | E37: Giai đoạn đầu có thể đặt 0đ (tự làm) hoặc thuê CTV part-time
B38: 6. Ngân sách mua Voucher sàn tài trợ khuyến mại | C38: 1000000 | D38: Marketing | E38: Mua voucher mồi để tặng đáp viên mới kích cầu
B39: 7. Phí giao dịch chuyển khoản Payout ngân hàng | C39: 300000 | D39: Biến phí | E39: ~150 lệnh chuyển khoản duyệt thưởng x 2.000đ/lệnh
B40: 8. Chi phí dự phòng phát sinh & bảo trì hệ thống | C40: 500000 | D40: Dự phòng | E40: Dự phòng lỗi, tải tăng đột biến, marketing học đường
B41: TỔNG CHI PHÍ VẬN HÀNH HÀNG THÁNG (TOTAL OPEX) | C41: =SUM(C33:C40) -> 0 | D41: VNĐ / tháng | E41: Tổng số tiền phải bỏ ra mỗi tháng để duy trì web/app

Sheet Dong Tien Hoi Von
B2: BẢNG TÍNH ĐIỂM HÒA VỐN & THỜI GIAN HOÀN VỐN (SOLVER & METRICS)
B3: Toàn bộ số liệu tự động tính toán. Khi bạn sửa dữ liệu bên Sheet 1, bảng này sẽ tự động giải toán lại ngay lập tức.
B5: I. DOANH THU THUẦN SÀN THỰC THU (PLATFORM NET REVENUE)
B6: Khoản Mục Doanh Thu Sàn | C6: Giá Trị (VNĐ) | D6: Tỷ Lệ | E6: Công Thức & Nguồn Tính
B7: 1. Doanh thu chiết khấu khảo sát (Take-Rate) | C7: ='Gia Dinh Dau Vao'!D21*'Gia Dinh Dau Vao'!C25 -> 0 | D7: =C7/C12 -> 0 | E7: Tính từ: Tổng tiền nạp Creator nhân Tỷ lệ Take-Rate
B8: 2. Doanh thu bán gói Ghim VIP + Push APK | C8: ='Gia Dinh Dau Vao'!C26*40000 -> 0 | D8: =C8/C12 -> 0 | E8: Tính từ: Số gói Ghim VIP nhân đơn giá 40.000đ/gói
B9: 3. Hoa hồng chiết khấu bán Voucher kho sàn | C9: ='Gia Dinh Dau Vao'!C27*'Gia Dinh Dau Vao'!C28 -> 0 | D9: =C9/C12 -> 0 | E9: Tính từ: Tổng giá trị Voucher bán ra nhân % Hoa hồng
B10: 4. Doanh thu phí rút tiền dưới 100k (2.000đ/lệnh) | C10: ='Gia Dinh Dau Vao'!C29*2000 -> 0 | D10: =C10/C12 -> 0 | E10: Tính từ: Số lệnh rút tiền nhân phí 2.000đ/lệnh
B11: 5. Thu nhập phụ trợ khác (Dự phòng) | C11: 0 | D11: 0 | E11: Nguồn thu phụ trợ khác trong tương lai
B12: TỔNG DOANH THU THUẦN SÀN (NET REVENUE) | C12: =SUM(C7:C11) -> 0 | D12: 100.0% | E12: Tổng tiền thực tế sàn giữ lại được mỗi tháng
B14: II. CHI PHÍ & LỢI NHUẬN HOẠT ĐỘNG RÒNG HÀNG THÁNG (EBITDA)
B15: Chỉ Số Tài Chính | C15: Giá Trị (VNĐ) | D15: Tỷ Suất | E15: Ý Nghĩa Quản Trị
B16: 1. Tổng Doanh Thu Thuần Hàng Tháng | C16: =C12 -> 0 | D16: 1 | E16: Chuyển từ mục Tổng Doanh Thu Thuần ở trên
B17: 2. Tổng Chi Phí Vận Hành Hàng Tháng (OpEx) | C17: ='Gia Dinh Dau Vao'!C41 -> 0 | D17: =C17/C16 -> 0 | E17: Server, email, cổng TT, nhân sự, voucher sàn, dự phòng
B18: 3. LỢI NHUẬN HOẠT ĐỘNG RÒNG (MONTHLY NET PROFIT) | C18: =C16-C17 -> 0 | D18: =C18/C16 -> 0 | E18: Tiền lời thực tế còn lại sau khi trừ hết chi phí vận hành
B20: III. PHÂN TÍCH ĐIỂM HÒA VỐN & THỜI GIAN HOÀN VỐN (SOLVER METRICS)
B21: Chỉ Số Tính Toán Hồi Vốn | C21: Kết Quả Tính Toán | D21: Đơn Vị | E21: Ý Nghĩa & Cách Diễn Giải
B22: 1. Doanh thu thuần để hòa vốn hàng tháng | C22: =C17 -> 0 | D22: VNĐ / tháng | E22: Sàn cần thu về tối thiểu số tiền này mỗi tháng để không lỗ
B23: 2. Tổng tiền Creator phải nạp (GMV) để hòa vốn | C23: =(C22-C8-C9-C10)/'Gia Dinh Dau Vao'!C25 -> 0 | D23: VNĐ nạp / tháng | E23: Tổng tiền nạp tối thiểu cần có để phần Take-Rate đủ bù OpEx
B24: 3. Số khách hàng Creator nạp tiền để hòa vốn | C24: =C23/('Gia Dinh Dau Vao'!D21/'Gia Dinh Dau Vao'!C21) -> 0 | D24: Người nạp / tháng | E24: Số khách nạp tiền bình quân mỗi tháng để sàn đạt điểm hòa vốn
B25: 4. Tổng vốn đầu tư ban đầu cần thu hồi (CapEx) | C25: ='Gia Dinh Dau Vao'!C13 -> 0 | D25: VNĐ | E25: Google Play, tên miền, BCT, quỹ trả thưởng mồi...
B26: 5. THỜI GIAN HOÀN VỐN ĐẦU TƯ (PAYBACK PERIOD) | C26: =IF(C18<=0, 999, C25/C18) -> 0 | D26: Tháng | E26: Số tháng để lợi nhuận tích lũy bù đắp 100% vốn đầu tư ban đầu
B27: 6. Tình trạng hoàn vốn (Solver Status) | C27: =IF(C18<=0, "CHƯA HÒA VỐN (ĐANG LỖ)", IF(C26<=6, "HOÀN VỐN NHANH (<6T)", IF(C26<=12, "HOÀN VỐN KHẢ QUAN (6-12T)", "HOÀN VỐN TRUNG HẠN (>12T)"))) -> 0 | D27: Đánh giá | E27: Tự động cảnh báo về tốc độ hồi vốn theo mức lãi ròng

Sheet Du Phong 12 Thang
B2: DỰ PHÓNG DÒNG TIỀN RÒNG 12 THÁNG & PHÂN TÍCH ĐỘ NHẠY
B3: Mô phỏng sự tăng trưởng người dùng qua 12 tháng và nhận diện chính xác thời điểm dòng tiền tích lũy chuyển sang số Dương.
B5: Chỉ Số / Mốc Thời Gian | C5: Khởi Tạo (T0) | D5: Tháng 1 | E5: Tháng 2 | F5: Tháng 3 | G5: Tháng 4 | H5: Tháng 5 | I5: Tháng 6 | J5: Tháng 7 | K5: Tháng 8 | L5: Tháng 9 | M5: Tháng 10 | N5: Tháng 11 | O5: Tháng 12 | P5: Tổng Cộng (12T)
B6: Hệ số tăng trưởng quy mô (%) | C6: - | D6: 0.4 | E6: 0.6 | F6: 0.8 | G6: 1 | H6: 1.2 | I6: 1.4 | J6: 1.7 | K6: 2 | L6: 2.3 | M6: 2.7 | N6: 3.1 | O6: -
B7: 1. Doanh Thu Thuần Sàn (VNĐ) | C7: 0 | D7: ='Dong Tien Hoi Von'!C12*D6 -> 0 | E7: ='Dong Tien Hoi Von'!C12*E6 -> 0 | F7: ='Dong Tien Hoi Von'!C12*F6 -> 0 | G7: ='Dong Tien Hoi Von'!C12*G6 -> 0 | H7: ='Dong Tien Hoi Von'!C12*H6 -> 0 | I7: ='Dong Tien Hoi Von'!C12*I6 -> 0 | J7: ='Dong Tien Hoi Von'!C12*J6 -> 0 | K7: ='Dong Tien Hoi Von'!C12*K6 -> 0 | L7: ='Dong Tien Hoi Von'!C12*L6 -> 0 | M7: ='Dong Tien Hoi Von'!C12*M6 -> 0 | N7: ='Dong Tien Hoi Von'!C12*N6 -> 0 | O7: =SUM(D7:N7) -> 0
B8: 2. Chi Phí Vận Hành OpEx (VNĐ) | C8: 0 | D8: ='Dong Tien Hoi Von'!C17*0.7 -> 0 | E8: ='Dong Tien Hoi Von'!C17*0.8 -> 0 | F8: ='Dong Tien Hoi Von'!C17*0.9 -> 0 | G8: ='Dong Tien Hoi Von'!C17*1.0 -> 0 | H8: ='Dong Tien Hoi Von'!C17*1.05 -> 0 | I8: ='Dong Tien Hoi Von'!C17*1.1 -> 0 | J8: ='Dong Tien Hoi Von'!C17*1.2 -> 0 | K8: ='Dong Tien Hoi Von'!C17*1.3 -> 0 | L8: ='Dong Tien Hoi Von'!C17*1.4 -> 0 | M8: ='Dong Tien Hoi Von'!C17*1.5 -> 0 | N8: ='Dong Tien Hoi Von'!C17*1.6 -> 0 | O8: =SUM(D8:N8) -> 0
B9: 3. Dòng Tiền Hoạt Động Tháng (VNĐ) | C9: 0 | D9: =D7-D8 -> 0 | E9: =E7-E8 -> 0 | F9: =F7-F8 -> 0 | G9: =G7-G8 -> 0 | H9: =H7-H8 -> 0 | I9: =I7-I8 -> 0 | J9: =J7-J8 -> 0 | K9: =K7-K8 -> 0 | ... N9: =N7-N8 -> 0 | O9: =SUM(D9:N9) -> 0
B10: 4. Vốn Đầu Tư Ban Đầu CapEx (VNĐ) | C10: ='Gia Dinh Dau Vao'!C13 -> 0 | D10: 0 | E10: 0 | F10: 0 | G10: 0 | H10: 0 | I10: 0 | J10: 0 | K10: 0 | L10: 0 | M10: 0 | N10: 0 | O10: =C10 -> 0
B11: 5. DÒNG TIỀN TÍCH LŨY (VNĐ) | C11: =-C10 -> 0 | D11: =C11+D9 -> 0 | E11: =D11+E9 -> 0 | F11: =E11+F9 -> 0 | G11: =F11+G9 -> 0 | H11: =G11+H9 -> 0 | I11: =H11+I9 -> 0 | J11: =I11+J9 -> 0 | K11: =J11+K9 -> 0 | ... N11: =M11+N9 -> 0 | O11: =N11 -> 0
B12: Trạng thái thu hồi vốn | C12: Âm vốn ban đầu | D12: =IF(D11>=0, "ĐÃ HỒI VỐN", "Đang thu hồi") -> 0 | E12: =IF(E11>=0, "ĐÃ HỒI VỐN", "Đang thu hồi") -> 0 | F12: =IF(F11>=0, "ĐÃ HỒI VỐN", "Đang thu hồi") -> 0 | G12: =IF(G11>=0, "ĐÃ HỒI VỐN", "Đang thu hồi") -> 0 | H12: =IF(H11>=0, "ĐÃ HỒI VỐN", "Đang thu hồi") -> 0 | I12: =IF(I11>=0, "ĐÃ HỒI VỐN", "Đang thu hồi") -> 0 | J12: =IF(J11>=0, "ĐÃ HỒI VỐN", "Đang thu hồi") -> 0 | K12: =IF(K11>=0, "ĐÃ HỒI VỐN", "Đang thu hồi") -> 0 | ... N12: =IF(N11>=0, "ĐÃ HỒI VỐN", "Đang thu hồi") -> 0 | O12: =IF(O11>=0, "CÓ LÃI RÒNG", "Chưa hồi đủ") -> 0
B15: BẢNG SO SÁNH ĐỘ NHẠY 3 KỊCH BẢN VẬN HÀNH (SCENARIO SENSITIVITY MATRIX)
B16: Kịch Bản Kinh Doanh | C16: Số Người Nạp / Tháng | D16: GMV Nạp (VNĐ) | E16: Doanh Thu Thuần (VNĐ) | F16: Chi Phí OpEx (VNĐ) | G16: Lãi Ròng / Tháng (VNĐ) | H16: Thời Gian Hồi Vốn (Tháng)
B17: 1. Kịch Bản Thận Trọng (Conservative - 50% kỳ vọng) | C17: ='Gia Dinh Dau Vao'!C21*0.5 -> 0 | D17: ='Gia Dinh Dau Vao'!D21*0.5 -> 0 | E17: ='Dong Tien Hoi Von'!C12*0.5 -> 0 | F17: ='Dong Tien Hoi Von'!C17*(1 + (0.5-1)*0.25) -> 0 | G17: =E17-F17 -> 0 | H17: =IF(G17<=0, 999, 'Dong Tien Hoi Von'!C25/G17) -> 0
B18: 2. Kịch Bản Cơ Sở (Base Case - 100% giả định) | C18: ='Gia Dinh Dau Vao'!C21*1.0 -> 0 | D18: ='Gia Dinh Dau Vao'!D21*1.0 -> 0 | E18: ='Dong Tien Hoi Von'!C12*1.0 -> 0 | F18: ='Dong Tien Hoi Von'!C17*(1 + (1.0-1)*0.25) -> 0 | G18: =E18-F18 -> 0 | H18: =IF(G18<=0, 999, 'Dong Tien Hoi Von'!C25/G18) -> 0
B19: 3. Kịch Bản Lạc Quan (Optimistic - 180% tăng trưởng) | C19: ='Gia Dinh Dau Vao'!C21*1.8 -> 0 | D19: ='Gia Dinh Dau Vao'!D21*1.8 -> 0 | E19: ='Dong Tien Hoi Von'!C12*1.8 -> 0 | F19: ='Dong Tien Hoi Von'!C17*(1 + (1.8-1)*0.25) -> 0 | G19: =E19-F19 -> 0 | H19: =IF(G19<=0, 999, 'Dong Tien Hoi Von'!C25/G19) -> 0
B21: Hướng dẫn sử dụng: | C21: Chỉ cần chỉnh sửa các số liệu giả định tại Sheet 1, toàn bộ bảng dự phóng 12 tháng và 3 kịch bản độ nhạy sẽ tự động giải toán (Solver) lại tức thì!
